fluxgraph/__init__.py
fluxgraph/analytics/__init__.py
fluxgraph/analytics/dashboard.py
fluxgraph/analytics/metrics_collector.py
fluxgraph/analytics/performance_monitor.py
fluxgraph/chains/__init__.py
fluxgraph/chains/batch.py
fluxgraph/chains/models.py
fluxgraph/chains/parsers.py
fluxgraph/chains/prompts.py
fluxgraph/chains/streaming.py
fluxgraph/connectors/__init__.py
fluxgraph/connectors/base.py
fluxgraph/connectors/postgres_connector.py
fluxgraph/connectors/salesforce_connector.py
fluxgraph/connectors/shopify_connector.py
fluxgraph/core/__init__.py
fluxgraph/core/adapter.py
fluxgraph/core/advanced_memory.py
fluxgraph/core/agent_cache.py
fluxgraph/core/agent_messaging.py
fluxgraph/core/app.py
fluxgraph/core/circuit_breaker.py
fluxgraph/core/cost_tracker.py
fluxgraph/core/enhanced_memory.py
fluxgraph/core/memory.py
fluxgraph/core/orchestrator.py
fluxgraph/core/orchestrator_advanced.py
fluxgraph/core/postgres_memory.py
fluxgraph/core/rag.py
fluxgraph/core/rbac.py
fluxgraph/core/registry.py
fluxgraph/core/retry.py
fluxgraph/core/session_manager.py
fluxgraph/core/smart_router.py
fluxgraph/core/streaming.py
fluxgraph/core/tool_registry.py
fluxgraph/core/universal_rag.py
fluxgraph/core/validation.py
fluxgraph/core/versioning.py
fluxgraph/core/workflow_graph.py
fluxgraph/crew/__init__.py
fluxgraph/crew/delegation.py
fluxgraph/crew/human.py
fluxgraph/crew/knowledge.py
fluxgraph/crew/role_agent.py
fluxgraph/crew/routing.py
fluxgraph/marketplace/templates.py
fluxgraph/models/__init__.py
fluxgraph/models/anthropic_provider.py
fluxgraph/models/builder.py
fluxgraph/models/easy.py
fluxgraph/models/factory.py
fluxgraph/models/gemini_provider.py
fluxgraph/models/groq_provider.py
fluxgraph/models/huggingface_provider.py
fluxgraph/models/ollama_provider.py
fluxgraph/models/openai_provider.py
fluxgraph/models/presets.py
fluxgraph/models/provider.py
fluxgraph/models/simple.py
fluxgraph/multimodal/processor.py
fluxgraph/orchestration/batch.py
fluxgraph/orchestration/handoff.py
fluxgraph-2.1.0.dist-info/licenses/LICENSE
fluxgraph-2.1.0.dist-info/METADATA
fluxgraph-2.1.0.dist-info/WHEEL
fluxgraph-2.1.0.dist-info/entry_points.txt
fluxgraph-2.1.0.dist-info/top_level.txt
fluxgraph-2.1.0.dist-info/RECORD
