Metadata-Version: 2.4
Name: fluxgraph
Version: 2.1.0
Summary: Production-grade AI agent orchestration framework with graph workflows, semantic caching, and hybrid memory. The complete alternative to LangGraph, CrewAI, and AutoGen.
Home-page: https://github.com/ihtesham-jahangir/fluxgraph
Author: Ihtesham Jahangir
Author-email: Ihtesham Jahangir <ceo@alphanetwork.com.pk>
Maintainer-email: Ihtesham Jahangir <ceo@alphanetwork.com.pk>
License: MIT
Project-URL: Homepage, https://github.com/ihtesham-jahangir/fluxgraph
Project-URL: Documentation, https://fluxgraph.readthedocs.io
Project-URL: Repository, https://github.com/ihtesham-jahangir/fluxgraph
Project-URL: Source, https://github.com/ihtesham-jahangir/fluxgraph
Project-URL: Bug Tracker, https://github.com/ihtesham-jahangir/fluxgraph/issues
Project-URL: Changelog, https://github.com/ihtesham-jahangir/fluxgraph/blob/main/CHANGELOG.md
Project-URL: Discord, https://discord.gg/Z9bAqjYvPc
Project-URL: Twitter, https://twitter.com/FluxGraphAI
Project-URL: LinkedIn, https://linkedin.com/in/ihtesham-jahangir
Keywords: ai,agents,llm,gpt,orchestration,multi-agent,autonomous-agents,langchain,langgraph,autogen,crewai,semantic-kernel,haystack,openai,anthropic,claude,gemini,groq,ollama,gpt-4,fastapi,async,rag,vector-database,embeddings,chromadb,workflow,workflow-graph,semantic-caching,hybrid-memory,enterprise,production,security,audit,compliance,rbac,hitl,human-in-the-loop,circuit-breaker,cost-tracking,agent-framework,ai-orchestration,llm-framework
Platform: any
Classifier: Development Status :: 5 - Production/Stable
Classifier: Intended Audience :: Developers
Classifier: Intended Audience :: Science/Research
Classifier: Intended Audience :: Information Technology
Classifier: License :: OSI Approved :: MIT License
Classifier: Operating System :: OS Independent
Classifier: Programming Language :: Python :: 3
Classifier: Programming Language :: Python :: 3.8
Classifier: Programming Language :: Python :: 3.9
Classifier: Programming Language :: Python :: 3.10
Classifier: Programming Language :: Python :: 3.11
Classifier: Programming Language :: Python :: 3.12
Classifier: Programming Language :: Python :: 3 :: Only
Classifier: Topic :: Software Development :: Libraries :: Python Modules
Classifier: Topic :: Software Development :: Libraries :: Application Frameworks
Classifier: Topic :: Scientific/Engineering :: Artificial Intelligence
Classifier: Topic :: Internet :: WWW/HTTP :: HTTP Servers
Classifier: Framework :: FastAPI
Classifier: Framework :: AsyncIO
Classifier: Typing :: Typed
Classifier: Natural Language :: English
Classifier: Environment :: Web Environment
Classifier: Environment :: Console
Requires-Python: >=3.8
License-File: LICENSE
Requires-Dist: fastapi>=0.104.0
Requires-Dist: uvicorn>=0.24.0
Requires-Dist: pydantic>=2.5.0
Requires-Dist: httpx>=0.25.0
Provides-Extra: p0
Requires-Dist: networkx>=3.1; extra == "p0"
Requires-Dist: sentence-transformers>=2.2.2; extra == "p0"
Requires-Dist: numpy>=1.24.0; extra == "p0"
Requires-Dist: faiss-cpu>=1.7.4; extra == "p0"
Provides-Extra: production
Requires-Dist: uvicorn[standard]>=0.24.0; extra == "production"
Requires-Dist: gunicorn>=21.0.0; extra == "production"
Requires-Dist: sse-starlette>=1.6.5; extra == "production"
Requires-Dist: python-multipart>=0.0.6; extra == "production"
Provides-Extra: security
Requires-Dist: pyjwt>=2.8.0; extra == "security"
Requires-Dist: cryptography>=41.0.0; extra == "security"
Requires-Dist: python-jose[cryptography]>=3.3.0; extra == "security"
Requires-Dist: passlib[bcrypt]>=1.7.4; extra == "security"
Provides-Extra: orchestration
Requires-Dist: celery>=5.3.4; extra == "orchestration"
Requires-Dist: redis>=5.0.0; extra == "orchestration"
Provides-Extra: rag
Requires-Dist: chromadb>=0.4.18; extra == "rag"
Requires-Dist: langchain>=0.1.0; extra == "rag"
Requires-Dist: sentence-transformers>=2.2.2; extra == "rag"
Requires-Dist: pypdf>=3.17.0; extra == "rag"
Requires-Dist: docx2txt>=0.8; extra == "rag"
Requires-Dist: unstructured>=0.11.0; extra == "rag"
Provides-Extra: postgres
Requires-Dist: psycopg2-binary>=2.9.9; extra == "postgres"
Requires-Dist: sqlalchemy>=2.0.23; extra == "postgres"
Provides-Extra: analytics
Requires-Dist: prometheus-client>=0.19.0; extra == "analytics"
Requires-Dist: plotly>=5.18.0; extra == "analytics"
Requires-Dist: pandas>=2.0.0; extra == "analytics"
Provides-Extra: chains
Requires-Dist: langchain-core>=0.1.0; extra == "chains"
Provides-Extra: tracing
Requires-Dist: opentelemetry-api>=1.20.0; extra == "tracing"
Requires-Dist: opentelemetry-sdk>=1.20.0; extra == "tracing"
Provides-Extra: dev
Requires-Dist: pytest>=7.4.3; extra == "dev"
Requires-Dist: pytest-asyncio>=0.21.1; extra == "dev"
Requires-Dist: pytest-cov>=4.1.0; extra == "dev"
Requires-Dist: black>=23.12.0; extra == "dev"
Requires-Dist: ruff>=0.1.0; extra == "dev"
Requires-Dist: mypy>=1.7.1; extra == "dev"
Requires-Dist: isort>=5.13.0; extra == "dev"
Requires-Dist: pre-commit>=3.5.0; extra == "dev"
Provides-Extra: test
Requires-Dist: pytest>=7.4.3; extra == "test"
Requires-Dist: pytest-asyncio>=0.21.1; extra == "test"
Requires-Dist: pytest-cov>=4.1.0; extra == "test"
Requires-Dist: httpx>=0.25.0; extra == "test"
Requires-Dist: faker>=20.1.0; extra == "test"
Provides-Extra: full
Requires-Dist: networkx>=3.1; extra == "full"
Requires-Dist: sentence-transformers>=2.2.2; extra == "full"
Requires-Dist: numpy>=1.24.0; extra == "full"
Requires-Dist: faiss-cpu>=1.7.4; extra == "full"
Requires-Dist: uvicorn[standard]>=0.24.0; extra == "full"
Requires-Dist: gunicorn>=21.0.0; extra == "full"
Requires-Dist: sse-starlette>=1.6.5; extra == "full"
Requires-Dist: python-multipart>=0.0.6; extra == "full"
Requires-Dist: celery>=5.3.4; extra == "full"
Requires-Dist: redis>=5.0.0; extra == "full"
Requires-Dist: chromadb>=0.4.18; extra == "full"
Requires-Dist: langchain>=0.1.0; extra == "full"
Requires-Dist: pypdf>=3.17.0; extra == "full"
Requires-Dist: docx2txt>=0.8; extra == "full"
Requires-Dist: psycopg2-binary>=2.9.9; extra == "full"
Requires-Dist: sqlalchemy>=2.0.23; extra == "full"
Requires-Dist: prometheus-client>=0.19.0; extra == "full"
Requires-Dist: plotly>=5.18.0; extra == "full"
Requires-Dist: pandas>=2.0.0; extra == "full"
Requires-Dist: langchain-core>=0.1.0; extra == "full"
Requires-Dist: opentelemetry-api>=1.20.0; extra == "full"
Requires-Dist: opentelemetry-sdk>=1.20.0; extra == "full"
Provides-Extra: all
Requires-Dist: networkx>=3.1; extra == "all"
Requires-Dist: sentence-transformers>=2.2.2; extra == "all"
Requires-Dist: numpy>=1.24.0; extra == "all"
Requires-Dist: faiss-cpu>=1.7.4; extra == "all"
Requires-Dist: uvicorn[standard]>=0.24.0; extra == "all"
Requires-Dist: gunicorn>=21.0.0; extra == "all"
Requires-Dist: sse-starlette>=1.6.5; extra == "all"
Requires-Dist: python-multipart>=0.0.6; extra == "all"
Requires-Dist: pyjwt>=2.8.0; extra == "all"
Requires-Dist: cryptography>=41.0.0; extra == "all"
Requires-Dist: python-jose[cryptography]>=3.3.0; extra == "all"
Requires-Dist: passlib[bcrypt]>=1.7.4; extra == "all"
Requires-Dist: celery>=5.3.4; extra == "all"
Requires-Dist: redis>=5.0.0; extra == "all"
Requires-Dist: chromadb>=0.4.18; extra == "all"
Requires-Dist: langchain>=0.1.0; extra == "all"
Requires-Dist: pypdf>=3.17.0; extra == "all"
Requires-Dist: docx2txt>=0.8; extra == "all"
Requires-Dist: psycopg2-binary>=2.9.9; extra == "all"
Requires-Dist: sqlalchemy>=2.0.23; extra == "all"
Requires-Dist: prometheus-client>=0.19.0; extra == "all"
Requires-Dist: plotly>=5.18.0; extra == "all"
Requires-Dist: pandas>=2.0.0; extra == "all"
Requires-Dist: langchain-core>=0.1.0; extra == "all"
Requires-Dist: opentelemetry-api>=1.20.0; extra == "all"
Requires-Dist: opentelemetry-sdk>=1.20.0; extra == "all"
Requires-Dist: pytest>=7.4.3; extra == "all"
Requires-Dist: pytest-asyncio>=0.21.1; extra == "all"
Requires-Dist: pytest-cov>=4.1.0; extra == "all"
Requires-Dist: black>=23.12.0; extra == "all"
Requires-Dist: ruff>=0.1.0; extra == "all"
Requires-Dist: mypy>=1.7.1; extra == "all"
Dynamic: author
Dynamic: home-page
Dynamic: license-file
Dynamic: platform
Dynamic: requires-python
